yamlreader.py
yamlreader-3.0.1.dist-info/entry_points.txt
yamlreader-3.0.1.dist-info/top_level.txt
yamlreader-3.0.1.dist-info/WHEEL
yamlreader-3.0.1.dist-info/metadata.json
yamlreader-3.0.1.dist-info/DESCRIPTION.rst
yamlreader-3.0.1.dist-info/METADATA
yamlreader-3.0.1.dist-info/RECORD
